osbot_jupyter/Deploy.py
osbot_jupyter/__init__.py
osbot_jupyter/api/CodeBuild_Jupyter.py
osbot_jupyter/api/CodeBuild_Jupyter_Helper.py
osbot_jupyter/api/Docker_Jupyter.py
osbot_jupyter/api/Jupyter_API.py
osbot_jupyter/api/Jupyter_Kernel.py
osbot_jupyter/api/Jupyter_Session.py
osbot_jupyter/api/Jupyter_Web.py
osbot_jupyter/api/Jupyter_Web_Cell.py
osbot_jupyter/api/Jypyter_API_Actions.py
osbot_jupyter/api/Kernel_Install.py
osbot_jupyter/api/Live_Notebook.py
osbot_jupyter/api/__init__.py
osbot_jupyter/api_js/Jp_Go_Js.py
osbot_jupyter/api_js/Jp_Vis_Js.py
osbot_jupyter/api_js/__init__.py
osbot_jupyter/api_notebook/Jp_GSheets.py
osbot_jupyter/api_notebook/Jp_Graph_Data.py
osbot_jupyter/api_notebook/Jp_Helper.py
osbot_jupyter/api_notebook/Jp_Jira.py
osbot_jupyter/api_notebook/__init__.py
osbot_jupyter/helpers/GSBot_Execution.py
osbot_jupyter/helpers/Test_Server.py
osbot_jupyter/helpers/__init__.py
osbot_jupyter/kernels/Echo_Kernel.py
osbot_jupyter/kernels/GSBot_Kernel.py
osbot_jupyter/kernels/PlotKernel.py
osbot_jupyter/kernels/__init__.py
osbot_jupyter/lambdas/__init__.py
osbot_jupyter/lambdas/browser.py
osbot_jupyter/lambdas/execute_python.py
osbot_jupyter/lambdas/nbconvert.py
osbot_jupyter/lambdas/osbot.py
osbot_jupyter/lambdas/screenshot.py
osbot_jupyter/lambdas/start_server.py
osbot_jupyter/notebook/__init__.py
osbot_jupyter/osbot/Jupyter_Commands.py
osbot_jupyter/osbot/__init__.py
osbot_jupyter-0.4.2.dist-info/LICENSE
osbot_jupyter-0.4.2.dist-info/METADATA
osbot_jupyter-0.4.2.dist-info/WHEEL
osbot_jupyter-0.4.2.dist-info/top_level.txt
osbot_jupyter-0.4.2.dist-info/RECORD
