Metadata-Version: 2.1
Name: osbot-jupyter
Version: 0.4.2
Summary: OWASP Security Bot - GSuite
Home-page: https://github.com/pbx-gs/OSBot-GSuite
Author: Dinis Cruz
Author-email: dinis.cruz@owasp.org
License: UNKNOWN
Platform: UNKNOWN
Classifier: Programming Language :: Python :: 3
Classifier: License :: OSI Approved :: MIT License
Classifier: Operating System :: OS Independent
